cuckoo/__init__.py
cuckoo/_cuckoo.py
pycuckoo-0.0.2.dist-info/LICENSE
pycuckoo-0.0.2.dist-info/METADATA
pycuckoo-0.0.2.dist-info/WHEEL
pycuckoo-0.0.2.dist-info/top_level.txt
pycuckoo-0.0.2.dist-info/RECORD
