Metadata-Version: 2.1
Name: pycuckoo
Version: 0.0.2
Summary: a cuckoo filter
Home-page: UNKNOWN
Author: mikeshardmind
Author-email: michael@michaelhall.tech
License: MIT
Platform: UNKNOWN
Classifier: Intended Audience :: Developers
Classifier: License :: OSI Approved :: MIT License
Classifier: Operating System :: OS Independent
Classifier: Programming Language :: Python :: 3 :: Only
Requires-Python: >=3
Requires-Dist: numpy
Requires-Dist: xxhash
